restful_client2/__init__.py
restful_client2/clients.py
tests/__init__.py
tests/test_clients.py
RESTful_Client2-1.0.0.dist-info/LICENSE
RESTful_Client2-1.0.0.dist-info/METADATA
RESTful_Client2-1.0.0.dist-info/WHEEL
RESTful_Client2-1.0.0.dist-info/top_level.txt
RESTful_Client2-1.0.0.dist-info/RECORD
