Metadata-Version: 2.1
Name: RESTful-Client2
Version: 1.0.0
Summary: RESTful is a simple API library for Humans, inspired by Python Requests
Home-page: https://github.com/johnbrandborg/restful-client2
Author: John Brandborg
Author-email: john.brandborg+pypi@pm.me
License: MIT
Project-URL: Source, https://github.com/johnbrandborg/restful-client2
Project-URL: Tracker, https://github.com/johnbrandborg/restful-client2/issues
Keywords: restful api crud
Platform: unix
Platform: linux
Platform: osx
Platform: cygwin
Platform: win32
Classifier: Development Status :: 5 - Production/Stable
Classifier: Intended Audience :: Developers
Classifier: License :: OSI Approved :: MIT License
Classifier: Operating System :: MacOS :: MacOS X
Classifier: Operating System :: Microsoft :: Windows
Classifier: Operating System :: POSIX
Classifier: Programming Language :: Python :: 3
Classifier: Programming Language :: Python :: 3 :: Only
Classifier: Programming Language :: Python :: 3.7
Classifier: Programming Language :: Python :: 3.8
Classifier: Programming Language :: Python :: 3.9
Classifier: Programming Language :: Python :: 3.10
Classifier: Programming Language :: Python :: 3.11
Classifier: Topic :: Software Development :: Libraries
Classifier: Topic :: Software Development :: Testing
Classifier: Topic :: Utilities
Requires-Python: >=3.7
License-File: LICENSE
Requires-Dist: certifi
Requires-Dist: urllib3
Provides-Extra: develop
Requires-Dist: flake8 ; extra == 'develop'
Requires-Dist: pytest ; extra == 'develop'
Requires-Dist: pytest-cov ; extra == 'develop'
